{"2024-05-31-2024-05-31": [{"Influencer": "marianherrrera", "Centralidad": 6.67}, {"Influencer": "GariaSabri98728", "Centralidad": 4.44}, {"Influencer": "santumaratea1", "Centralidad": 4.44}, {"Influencer": "sotoplasma", "Centralidad": 0.0}, {"Influencer": "thecoke0", "Centralidad": 0.0}, {"Influencer": "Mariangpod", "Centralidad": 0.0}, {"Influencer": "nomesemisigno", "Centralidad": 0.0}, {"Influencer": "PabloOliveraDaS", "Centralidad": 0.0}, {"Influencer": "_xaxrxx_", "Centralidad": 0.0}, {"Influencer": "elcancillercom", "Centralidad": 0.0}, {"Influencer": "Jose69barrios", "Centralidad": 0.0}]}